README.md
setup.py
jebpy/__init__.py
jebpy/input_types.py
jebpy/is_strings.py
jebpy/password_generator.py
jebpy/percentage.py
jebpy.egg-info/PKG-INFO
jebpy.egg-info/SOURCES.txt
jebpy.egg-info/dependency_links.txt
jebpy.egg-info/top_level.txt