Metadata-Version: 2.1
Name: jebpy
Version: 1.0.0
Summary: Python module made by jebbarbas
Home-page: https://github.com/jebbarbas/jebpy
Author: jebbarbas
Author-email: enriquebarbozajeb@gmail.com
License: NOTFOUND
Download-URL: https://github.com/jebbarbas/jebpy/tarball/v1.0.0
Keywords: jebpy,input,password,percentage,weight,probability,is
Platform: UNKNOWN
Classifier: Development Status :: 5 - Production/Stable
Classifier: Intended Audience :: Developers
Classifier: Topic :: Software Development :: Build Tools
Classifier: Programming Language :: Python :: 3.4
Classifier: Programming Language :: Python :: 3.5
Classifier: Programming Language :: Python :: 3.6
Classifier: Programming Language :: Python :: 3.7
Classifier: Programming Language :: Python :: 3.8
